odoo/addons/ssi_partner_evaluation/README.rst
odoo/addons/ssi_partner_evaluation/__init__.py
odoo/addons/ssi_partner_evaluation/__manifest__.py
odoo/addons/ssi_partner_evaluation/menu.xml
odoo/addons/ssi_partner_evaluation/data/base_automation_data.xml
odoo/addons/ssi_partner_evaluation/data/ir_actions_server_data.xml
odoo/addons/ssi_partner_evaluation/data/approval_template/partner_batch_evaluation.xml
odoo/addons/ssi_partner_evaluation/data/approval_template/partner_evaluation.xml
odoo/addons/ssi_partner_evaluation/data/ir_sequence/partner_batch_evaluation.xml
odoo/addons/ssi_partner_evaluation/data/ir_sequence/partner_evaluation.xml
odoo/addons/ssi_partner_evaluation/data/policy_template/partner_batch_evaluation.xml
odoo/addons/ssi_partner_evaluation/data/policy_template/partner_evaluation.xml
odoo/addons/ssi_partner_evaluation/data/sequence_template/partner_batch_evaluation.xml
odoo/addons/ssi_partner_evaluation/data/sequence_template/partner_evaluation.xml
odoo/addons/ssi_partner_evaluation/models/__init__.py
odoo/addons/ssi_partner_evaluation/models/partner_batch_evaluation.py
odoo/addons/ssi_partner_evaluation/models/partner_evaluation.py
odoo/addons/ssi_partner_evaluation/models/partner_evaluation_item.py
odoo/addons/ssi_partner_evaluation/models/partner_evaluation_question.py
odoo/addons/ssi_partner_evaluation/models/partner_evaluation_question_type.py
odoo/addons/ssi_partner_evaluation/models/partner_evaluation_result.py
odoo/addons/ssi_partner_evaluation/models/partner_evaluation_type.py
odoo/addons/ssi_partner_evaluation/models/partner_evaluation_type_question.py
odoo/addons/ssi_partner_evaluation/models/partner_evaluation_value_item.py
odoo/addons/ssi_partner_evaluation/models/partner_evaluation_value_set.py
odoo/addons/ssi_partner_evaluation/models/partner_evaluation_value_set_item.py
odoo/addons/ssi_partner_evaluation/models/res_partner.py
odoo/addons/ssi_partner_evaluation/models/res_partner_evaluation_result.py
odoo14_addon_ssi_partner_evaluation-14.0.4.1.0.dist-info/METADATA
odoo14_addon_ssi_partner_evaluation-14.0.4.1.0.dist-info/WHEEL
odoo14_addon_ssi_partner_evaluation-14.0.4.1.0.dist-info/top_level.txt
odoo14_addon_ssi_partner_evaluation-14.0.4.1.0.dist-info/RECORD
